proto-stubs/__init__.pyi
proto-stubs/_file_info.pyi
proto-stubs/_package_info.pyi
proto-stubs/datetime_helpers.pyi
proto-stubs/enums.pyi
proto-stubs/fields.pyi
proto-stubs/marshal/__init__.pyi
proto-stubs/marshal/collections/__init__.pyi
proto-stubs/marshal/collections/maps.pyi
proto-stubs/marshal/collections/repeated.pyi
proto-stubs/marshal/compat.pyi
proto-stubs/marshal/marshal.pyi
proto-stubs/marshal/rules/__init__.pyi
proto-stubs/marshal/rules/dates.pyi
proto-stubs/marshal/rules/enums.pyi
proto-stubs/marshal/rules/message.pyi
proto-stubs/marshal/rules/struct.pyi
proto-stubs/marshal/rules/wrappers.pyi
proto-stubs/message.pyi
proto-stubs/modules.pyi
proto-stubs/primitives.pyi
proto-stubs/utils.pyi
proto_plus_stubs-0.7.0.dist-info/LICENSE
proto_plus_stubs-0.7.0.dist-info/METADATA
proto_plus_stubs-0.7.0.dist-info/WHEEL
proto_plus_stubs-0.7.0.dist-info/RECORD
