Metadata-Version: 2.1
Name: proto-plus-stubs
Version: 0.7.0
Summary: Type stubs for proto-plus
Home-page: https://github.com/henribru/proto-plus-stubs
License: Apache-2.0
Author: Henrik Bruåsdal
Author-email: henrik.bruasdal@gmail.com
Requires-Python: >=3.7,<4.0
Classifier: License :: OSI Approved :: Apache Software License
Classifier: Programming Language :: Python :: 3
Classifier: Programming Language :: Python :: 3.7
Classifier: Programming Language :: Python :: 3.8
Classifier: Programming Language :: Python :: 3.9
Classifier: Programming Language :: Python :: 3.10
Classifier: Programming Language :: Python :: 3.11
Classifier: Programming Language :: Python :: 3.12
Classifier: Typing :: Stubs Only
Requires-Dist: proto-plus (>=1.18.0)
Requires-Dist: types-protobuf (>=3.17.4)
Project-URL: Repository, https://github.com/henribru/proto-plus-stubs
